src/__init__.py
src/chat.py
src/generators.py
src/utils.py
src/engines/__init__.py
src/engines/llm.py
src/engines/lvm.py
src/engines/memory.py
src/engines/reporting.py
askdoc-0.1.1.dist-info/METADATA
askdoc-0.1.1.dist-info/WHEEL
askdoc-0.1.1.dist-info/entry_points.txt
askdoc-0.1.1.dist-info/top_level.txt
askdoc-0.1.1.dist-info/RECORD
