Metadata-Version: 2.1
Name: askdoc
Version: 0.1.1
Summary: Ask a personal doctor for your medical queries
Home-page: https://github.com/romitjain/askdoc
Author: Romit
Author-email: romit.73@gmail.com
Classifier: Programming Language :: Python :: 3
Classifier: License :: OSI Approved :: MIT License
Classifier: Operating System :: OS Independent
Requires-Dist: loguru ==0.7.2
Requires-Dist: gradio ==4.19.2
Requires-Dist: openai ==1.13.3
Requires-Dist: backoff ==2.2.1
Requires-Dist: numpy ==1.24.3
Requires-Dist: sentence-transformers ==2.3.1
Requires-Dist: pytesseract ==0.3.10
Requires-Dist: pdf2image ==1.17.0
Requires-Dist: python-dotenv ==0.21.1
